odoo/addons/edi_backend_partner/README.rst
odoo/addons/edi_backend_partner/__init__.py
odoo/addons/edi_backend_partner/__manifest__.py
odoo/addons/edi_backend_partner/i18n/edi_backend_partner.pot
odoo/addons/edi_backend_partner/models/__init__.py
odoo/addons/edi_backend_partner/models/edi_backend.py
odoo/addons/edi_backend_partner/models/res_partner.py
odoo/addons/edi_backend_partner/readme/CONTRIBUTORS.rst
odoo/addons/edi_backend_partner/readme/DESCRIPTION.rst
odoo/addons/edi_backend_partner/static/description/icon.png
odoo/addons/edi_backend_partner/static/description/index.html
odoo/addons/edi_backend_partner/tests/__init__.py
odoo/addons/edi_backend_partner/tests/test_edi_backend_partner.py
odoo/addons/edi_backend_partner/views/edi_backend_views.xml
odoo/addons/edi_backend_partner/views/res_partner_views.xml
odoo13_addon_edi_backend_partner-13.0.1.0.1.dist-info/METADATA
odoo13_addon_edi_backend_partner-13.0.1.0.1.dist-info/WHEEL
odoo13_addon_edi_backend_partner-13.0.1.0.1.dist-info/top_level.txt
odoo13_addon_edi_backend_partner-13.0.1.0.1.dist-info/RECORD
