Metadata-Version: 2.1
Name: odoo13-addon-edi-backend-partner
Version: 13.0.1.0.1
Summary: add the a partner field in EDI backend
Home-page: https://github.com/OCA/edi
Author: ForgeFlow, Odoo Community Association (OCA)
Author-email: support@odoo-community.org
License: LGPL-3
Platform: UNKNOWN
Classifier: Programming Language :: Python
Classifier: Framework :: Odoo
Classifier: Framework :: Odoo :: 13.0
Classifier: License :: OSI Approved :: GNU Lesser General Public License v3 (LGPLv3)
Classifier: Development Status :: 4 - Beta
Requires-Python: >=3.5
Requires-Dist: odoo13-addon-edi
Requires-Dist: odoo (<13.1dev,>=13.0a)
